<reservation>
  <f:family>
    <f:familyElement>
      <f:name>Ramon</f:name>
      <f:birthDate>2006-08-13</f:birthDate>
    </f:familyElement>
    <f:familyElement>
      <f:name>Sara</f:name>
      <f:birthDate>1961-06-07</f:birthDate>
    </f:familyElement>
    <f:familyElement>
      <f:name>Ana</f:name>
      <f:birthDate>2012-10-09</f:birthDate>
    </f:familyElement>
    <f:emergencyContact>123123123</f:emergencyContact>
    <f:origin>
      <gd:countryName>Italy</gd:countryName>
      <gd:cityName>Milan</gd:cityName>
    </f:origin>
    <f:reservationDates>
      <f:numberOfDays>5</f:numberOfDays>
      <f:preferedDates>2022-11-06</f:preferedDates>
      <f:preferedDates>2022-11-01</f:preferedDates>
      <f:preferedDates>2022-09-09</f:preferedDates>
      <f:preferedDates>2022-10-02</f:preferedDates>
      <f:preferedDates>2022-09-22</f:preferedDates>
    </f:reservationDates>
  </f:family>
</reservation>