<reservation>
  <f:family>
    <f:familyElement>
      <f:name>Marta</f:name>
      <f:birthDate>2010-05-23</f:birthDate>
    </f:familyElement>
    <f:familyElement>
      <f:name>Ramon</f:name>
      <f:birthDate>1994-11-20</f:birthDate>
    </f:familyElement>
    <f:familyElement>
      <f:name>Ramon</f:name>
      <f:birthDate>2001-06-26</f:birthDate>
    </f:familyElement>
    <f:familyElement>
      <f:name>Laura</f:name>
      <f:birthDate>2009-08-28</f:birthDate>
    </f:familyElement>
    <f:familyElement>
      <f:name>Carla</f:name>
      <f:birthDate>2008-04-25</f:birthDate>
    </f:familyElement>
    <f:emergencyContact>944955966</f:emergencyContact>
    <f:origin>
      <gd:countryName>United Kingdom</gd:countryName>
      <gd:cityName>Liverpool</gd:cityName>
    </f:origin>
    <f:reservationDates>
      <f:numberOfDays>4</f:numberOfDays>
      <f:preferedDates>2022-12-07</f:preferedDates>
      <f:preferedDates>2022-10-08</f:preferedDates>
      <f:preferedDates>2022-11-14</f:preferedDates>
      <f:preferedDates>2022-09-22</f:preferedDates>
    </f:reservationDates>
  </f:family>
</reservation>