<reservation>
  <f:family>
    <f:familyElement>
      <f:name>Carla</f:name>
      <f:birthDate>2019-08-06</f:birthDate>
    </f:familyElement>
    <f:familyElement>
      <f:name>Carla</f:name>
      <f:birthDate>2004-01-13</f:birthDate>
    </f:familyElement>
    <f:familyElement>
      <f:name>Pedro</f:name>
      <f:birthDate>2004-09-22</f:birthDate>
    </f:familyElement>
    <f:emergencyContact>256123456</f:emergencyContact>
    <f:origin>
      <gd:countryName>France</gd:countryName>
      <gd:cityName>Marseille</gd:cityName>
    </f:origin>
    <f:reservationDates>
      <f:numberOfDays>1</f:numberOfDays>
      <f:preferedDates>2022-11-19</f:preferedDates>
    </f:reservationDates>
  </f:family>
</reservation>