<reservation>
  <f:family>
    <f:familyElement>
      <f:name>Carlos</f:name>
      <f:birthDate>2003-01-21</f:birthDate>
    </f:familyElement>
    <f:familyElement>
      <f:name>Carla</f:name>
      <f:birthDate>2009-10-10</f:birthDate>
    </f:familyElement>
    <f:familyElement>
      <f:name>Carmen</f:name>
      <f:birthDate>2003-03-13</f:birthDate>
    </f:familyElement>
    <f:familyElement>
      <f:name>Luis</f:name>
      <f:birthDate>2013-06-28</f:birthDate>
    </f:familyElement>
    <f:emergencyContact>351234567</f:emergencyContact>
    <f:origin>
      <gd:countryName>Brazil</gd:countryName>
      <gd:cityName>Brasilia</gd:cityName>
    </f:origin>
    <f:reservationDates>
      <f:numberOfDays>1</f:numberOfDays>
      <f:preferedDates>2022-10-11</f:preferedDates>
    </f:reservationDates>
  </f:family>
</reservation>