<reservation>
  <f:family>
    <f:familyElement>
      <f:name>Jose</f:name>
      <f:birthDate>1991-06-01</f:birthDate>
    </f:familyElement>
    <f:familyElement>
      <f:name>Jose</f:name>
      <f:birthDate>2020-09-18</f:birthDate>
    </f:familyElement>
    <f:familyElement>
      <f:name>Pablo</f:name>
      <f:birthDate>2006-10-05</f:birthDate>
    </f:familyElement>
    <f:familyElement>
      <f:name>Martina</f:name>
      <f:birthDate>2000-01-13</f:birthDate>
    </f:familyElement>
    <f:emergencyContact>256123456</f:emergencyContact>
    <f:origin>
      <gd:countryName>Portugal</gd:countryName>
      <gd:cityName>Porto</gd:cityName>
    </f:origin>
    <f:reservationDates>
      <f:numberOfDays>3</f:numberOfDays>
      <f:preferedDates>2022-10-16</f:preferedDates>
      <f:preferedDates>2022-11-17</f:preferedDates>
      <f:preferedDates>2022-09-13</f:preferedDates>
    </f:reservationDates>
  </f:family>
</reservation>