<reservation>
  <f:family>
    <f:familyElement>
      <f:name>Luis</f:name>
      <f:birthDate>2015-08-20</f:birthDate>
    </f:familyElement>
    <f:familyElement>
      <f:name>Carlos</f:name>
      <f:birthDate>2006-10-05</f:birthDate>
    </f:familyElement>
    <f:familyElement>
      <f:name>Ana</f:name>
      <f:birthDate>2008-04-25</f:birthDate>
    </f:familyElement>
    <f:familyElement>
      <f:name>Laura</f:name>
      <f:birthDate>2016-01-18</f:birthDate>
    </f:familyElement>
    <f:familyElement>
      <f:name>Ramon</f:name>
      <f:birthDate>1998-05-19</f:birthDate>
    </f:familyElement>
    <f:emergencyContact>912341234</f:emergencyContact>
    <f:origin>
      <gd:countryName>Germany</gd:countryName>
      <gd:cityName>Frankfurt</gd:cityName>
    </f:origin>
    <f:reservationDates>
      <f:numberOfDays>3</f:numberOfDays>
      <f:preferedDates>2022-10-22</f:preferedDates>
      <f:preferedDates>2022-10-16</f:preferedDates>
      <f:preferedDates>2022-11-23</f:preferedDates>
    </f:reservationDates>
  </f:family>
</reservation>