<reservation>
  <f:family>
    <f:familyElement>
      <f:name>Jorge</f:name>
      <f:birthDate>2020-05-17</f:birthDate>
    </f:familyElement>
    <f:familyElement>
      <f:name>Carlos</f:name>
      <f:birthDate>2004-09-22</f:birthDate>
    </f:familyElement>
    <f:familyElement>
      <f:name>John</f:name>
      <f:birthDate>2007-02-03</f:birthDate>
    </f:familyElement>
    <f:familyElement>
      <f:name>Sofia</f:name>
      <f:birthDate>2018-05-23</f:birthDate>
    </f:familyElement>
    <f:emergencyContact>351234567</f:emergencyContact>
    <f:origin>
      <gd:countryName>United Kingdom</gd:countryName>
      <gd:cityName>London</gd:cityName>
    </f:origin>
    <f:reservationDates>
      <f:numberOfDays>3</f:numberOfDays>
      <f:preferedDates>2022-11-17</f:preferedDates>
      <f:preferedDates>2022-12-17</f:preferedDates>
      <f:preferedDates>2022-10-18</f:preferedDates>
    </f:reservationDates>
  </f:family>
</reservation>