<reservation>
  <f:family>
    <f:familyElement>
      <f:name>Ana</f:name>
      <f:birthDate>2001-02-01</f:birthDate>
    </f:familyElement>
    <f:familyElement>
      <f:name>Ramon</f:name>
      <f:birthDate>1996-07-07</f:birthDate>
    </f:familyElement>
    <f:familyElement>
      <f:name>John</f:name>
      <f:birthDate>2011-11-16</f:birthDate>
    </f:familyElement>
    <f:familyElement>
      <f:name>Pablo</f:name>
      <f:birthDate>2001-05-16</f:birthDate>
    </f:familyElement>
    <f:familyElement>
      <f:name>Ramon</f:name>
      <f:birthDate>2003-04-07</f:birthDate>
    </f:familyElement>
    <f:familyElement>
      <f:name>Ana</f:name>
      <f:birthDate>2013-05-04</f:birthDate>
    </f:familyElement>
    <f:emergencyContact>944955966</f:emergencyContact>
    <f:origin>
      <gd:countryName>Portugal</gd:countryName>
      <gd:cityName>Funchal</gd:cityName>
    </f:origin>
    <f:reservationDates>
      <f:numberOfDays>3</f:numberOfDays>
      <f:preferedDates>2022-09-20</f:preferedDates>
      <f:preferedDates>2022-12-08</f:preferedDates>
      <f:preferedDates>2022-10-07</f:preferedDates>
    </f:reservationDates>
  </f:family>
</reservation>