<reservation>
  <f:family>
    <f:familyElement>
      <f:name>Jose</f:name>
      <f:birthDate>1970-02-24</f:birthDate>
    </f:familyElement>
    <f:familyElement>
      <f:name>Pilar</f:name>
      <f:birthDate>1979-02-25</f:birthDate>
    </f:familyElement>
    <f:familyElement>
      <f:name>Carla</f:name>
      <f:birthDate>2002-04-28</f:birthDate>
    </f:familyElement>
    <f:familyElement>
      <f:name>Luis</f:name>
      <f:birthDate>2003-04-07</f:birthDate>
    </f:familyElement>
    <f:familyElement>
      <f:name>Carmen</f:name>
      <f:birthDate>2020-02-02</f:birthDate>
    </f:familyElement>
    <f:emergencyContact>944955966</f:emergencyContact>
    <f:origin>
      <gd:countryName>Canada</gd:countryName>
      <gd:cityName>Vancouver</gd:cityName>
    </f:origin>
    <f:reservationDates>
      <f:numberOfDays>5</f:numberOfDays>
      <f:preferedDates>2022-10-09</f:preferedDates>
      <f:preferedDates>2022-09-02</f:preferedDates>
      <f:preferedDates>2022-12-14</f:preferedDates>
      <f:preferedDates>2022-10-12</f:preferedDates>
      <f:preferedDates>2022-09-01</f:preferedDates>
    </f:reservationDates>
  </f:family>
</reservation>