<reservation>
  <f:family>
    <f:familyElement>
      <f:name>Sofia</f:name>
      <f:birthDate>2005-10-05</f:birthDate>
    </f:familyElement>
    <f:familyElement>
      <f:name>Laura</f:name>
      <f:birthDate>1995-10-25</f:birthDate>
    </f:familyElement>
    <f:familyElement>
      <f:name>Carmen</f:name>
      <f:birthDate>1989-10-23</f:birthDate>
    </f:familyElement>
    <f:familyElement>
      <f:name>Maria</f:name>
      <f:birthDate>1990-05-23</f:birthDate>
    </f:familyElement>
    <f:familyElement>
      <f:name>Jorge</f:name>
      <f:birthDate>1993-05-16</f:birthDate>
    </f:familyElement>
    <f:familyElement>
      <f:name>John</f:name>
      <f:birthDate>1974-09-18</f:birthDate>
    </f:familyElement>
    <f:familyElement>
      <f:name>Pilar</f:name>
      <f:birthDate>1964-11-10</f:birthDate>
    </f:familyElement>
    <f:emergencyContact>912341234</f:emergencyContact>
    <f:origin>
      <gd:countryName>France</gd:countryName>
      <gd:cityName>Lyon</gd:cityName>
    </f:origin>
    <f:reservationDates>
      <f:numberOfDays>1</f:numberOfDays>
      <f:preferedDates>2022-12-10</f:preferedDates>
    </f:reservationDates>
  </f:family>
</reservation>