<reservation>
  <f:family>
    <f:familyElement>
      <f:name>Marta</f:name>
      <f:birthDate>2013-04-10</f:birthDate>
    </f:familyElement>
    <f:familyElement>
      <f:name>John</f:name>
      <f:birthDate>2019-05-19</f:birthDate>
    </f:familyElement>
    <f:familyElement>
      <f:name>Jose</f:name>
      <f:birthDate>2015-07-27</f:birthDate>
    </f:familyElement>
    <f:familyElement>
      <f:name>John</f:name>
      <f:birthDate>1990-08-24</f:birthDate>
    </f:familyElement>
    <f:familyElement>
      <f:name>Jose</f:name>
      <f:birthDate>2010-03-16</f:birthDate>
    </f:familyElement>
    <f:familyElement>
      <f:name>Sofia</f:name>
      <f:birthDate>2020-01-08</f:birthDate>
    </f:familyElement>
    <f:emergencyContact>911922933</f:emergencyContact>
    <f:origin>
      <gd:countryName>Italy</gd:countryName>
      <gd:cityName>Milan</gd:cityName>
    </f:origin>
    <f:reservationDates>
      <f:numberOfDays>1</f:numberOfDays>
      <f:preferedDates>2022-11-09</f:preferedDates>
    </f:reservationDates>
  </f:family>
</reservation>